LICENCE.txt
README.txt
setup.py
python_laodt/__init__.py
python_laodt.egg-info/PKG-INFO
python_laodt.egg-info/SOURCES.txt
python_laodt.egg-info/dependency_links.txt
python_laodt.egg-info/top_level.txt