Metadata-Version: 2.1
Name: python-laodt
Version: 0.7.2
Summary: Pyhon LaoDT Libary
Home-page: 
Author: barlardcuda
Author-email: barluscuda@gmail.com
License: BLCD1234
Keywords: pythonlaodt
Classifier: Development Status :: 5 - Production/Stable
Classifier: Intended Audience :: Education
Classifier: Operating System :: OS Independent
Classifier: License :: OSI Approved :: MIT License
Classifier: Programming Language :: Python :: 3
License-File: LICENCE.txt
